{"players": [{"account_id": 50794045, "player_slot": 0, "hero_id": 110, "item_0": 48, "item_1": 36, "item_2": 190, "item_3": 46, "item_4": 259, "item_5": 119, "backpack_0": 0, "backpack_1": 0, "backpack_2": 0, "kills": 0, "deaths": 5, "assists": 10, "leaver_status": 0, "last_hits": 134, "denies": 0, "gold_per_min": 427, "xp_per_min": 476, "level": 18, "hero_damage": 14471, "tower_damage": 723, "hero_healing": 286, "gold": 264, "gold_spent": 13710, "scaled_hero_damage": 10094, "scaled_tower_damage": 414, "scaled_hero_healing": 160, "ability_upgrades": [{"ability": 5623, "time": 287, "level": 1}, {"ability": 5625, "time": 433, "level": 2}, {"ability": 5625, "time": 462, "level": 3}, {"ability": 5623, "time": 558, "level": 4}, {"ability": 5625, "time": 640, "level": 5}, {"ability": 5630, "time": 732, "level": 6}, {"ability": 5625, "time": 866, "level": 7}, {"ability": 5623, "time": 1019, "level": 8}, {"ability": 5623, "time": 1145, "level": 9}, {"ability": 5949, "time": 1236, "level": 10}, {"ability": 5626, "time": 1369, "level": 11}, {"ability": 5630, "time": 1536, "level": 12}, {"ability": 5626, "time": 1616, "level": 13}, {"ability": 6401, "time": 1778, "level": 14}, {"ability": 5626, "time": 1779, "level": 15}, {"ability": 5626, "time": 1868, "level": 16}, {"ability": 5630, "time": 2093, "level": 17}], "hero_name": "Phoenix", "item_0_name": "Boots of Travel", "item_1_name": "Magic Wand", "item_2_name": "Veil of Discord", "item_3_name": "Town Portal Scroll", "item_5_name": "Shiva's Guard", "leaver_status_name": "NONE", "leaver_status_description": "finished match, no abandon"}, {"account_id": 73860171, "player_slot": 1, "hero_id": 114, "item_0": 63, "item_1": 152, "item_2": 139, "item_3": 145, "item_4": 160, "item_5": 0, "backpack_0": 0, "backpack_1": 0, "backpack_2": 46, "kills": 10, "deaths": 0, "assists": 11, "leaver_status": 0, "last_hits": 331, "denies": 34, "gold_per_min": 796, "xp_per_min": 763, "level": 23, "hero_damage": 26012, "tower_damage": 9667, "hero_healing": 0, "gold": 5558, "gold_spent": 20550, "scaled_hero_damage": 16460, "scaled_tower_damage": 6580, "scaled_hero_healing": 0, "ability_upgrades": [{"ability": 5723, "time": 353, "level": 1}, {"ability": 5716, "time": 429, "level": 2}, {"ability": 5723, "time": 534, "level": 3}, {"ability": 5721, "time": 556, "level": 4}, {"ability": 5723, "time": 655, "level": 5}, {"ability": 5725, "time": 721, "level": 6}, {"ability": 5716, "time": 803, "level": 7}, {"ability": 5716, "time": 890, "level": 8}, {"ability": 5716, "time": 983, "level": 9}, {"ability": 5906, "time": 1065, "level": 10}, {"ability": 5721, "time": 1090, "level": 11}, {"ability": 5725, "time": 1195, "level": 12}, {"ability": 5721, "time": 1262, "level": 13}, {"ability": 5721, "time": 1421, "level": 14}, {"ability": 6421, "time": 1471, "level": 15}, {"ability": 5723, "time": 1587, "level": 16}, {"ability": 5725, "time": 1713, "level": 17}, {"ability": 6303, "time": 1804, "level": 18}], "hero_name": "Monkey King", "item_0_name": "Power Treads", "item_1_name": "Shadow Blade", "item_2_name": "Butterfly", "item_3_name": "Battle Fury", "item_4_name": "Eye of Skadi", "leaver_status_name": "NONE", "leaver_status_description": "finished match, no abandon"}, {"account_id": 376886463, "player_slot": 2, "hero_id": 68, "item_0": 214, "item_1": 41, "item_2": 43, "item_3": 244, "item_4": 30, "item_5": 36, "backpack_0": 46, "backpack_1": 0, "backpack_2": 0, "kills": 4, "deaths": 5, "assists": 14, "leaver_status": 0, "last_hits": 22, "denies": 5, "gold_per_min": 315, "xp_per_min": 389, "level": 16, "hero_damage": 10859, "tower_damage": 333, "hero_healing": 0, "gold": 3149, "gold_spent": 7000, "scaled_hero_damage": 7176, "scaled_tower_damage": 193, "scaled_hero_healing": 0, "ability_upgrades": [{"ability": 5347, "time": 288, "level": 1}, {"ability": 5345, "time": 485, "level": 2}, {"ability": 5345, "time": 596, "level": 3}, {"ability": 5346, "time": 752, "level": 4}, {"ability": 5345, "time": 970, "level": 5}, {"ability": 5348, "time": 1189, "level": 6}, {"ability": 5345, "time": 1330, "level": 7}, {"ability": 5347, "time": 1435, "level": 8}, {"ability": 5347, "time": 1523, "level": 9}, {"ability": 5989, "time": 1640, "level": 10}, {"ability": 5346, "time": 1682, "level": 11}, {"ability": 5348, "time": 1755, "level": 12}, {"ability": 5347, "time": 1863, "level": 13}, {"ability": 5346, "time": 1988, "level": 14}, {"ability": 6079, "time": 2106, "level": 15}, {"ability": 5346, "time": 2184, "level": 16}], "hero_name": "Ancient Apparition", "item_0_name": "Tranquil Boots", "item_1_name": "Bottle", "item_2_name": "Sentry Ward", "item_3_name": "Wind Lace", "item_4_name": "Gem of True Sight", "item_5_name": "Magic Wand", "leaver_status_name": "NONE", "leaver_status_description": "finished match, no abandon"}, {"account_id": 81807745, "player_slot": 3, "hero_id": 23, "item_0": 13, "item_1": 149, "item_2": 151, "item_3": 0, "item_4": 50, "item_5": 152, "backpack_0": 0, "backpack_1": 0, "backpack_2": 0, "kills": 2, "deaths": 3, "assists": 12, "leaver_status": 0, "last_hits": 116, "denies": 2, "gold_per_min": 412, "xp_per_min": 378, "level": 16, "hero_damage": 6052, "tower_damage": 1663, "hero_healing": 0, "gold": 3159, "gold_spent": 10165, "scaled_hero_damage": 4185, "scaled_tower_damage": 1124, "scaled_hero_healing": 0, "ability_upgrades": [{"ability": 5031, "time": 331, "level": 1}, {"ability": 5033, "time": 474, "level": 2}, {"ability": 5033, "time": 593, "level": 3}, {"ability": 5031, "time": 798, "level": 4}, {"ability": 5035, "time": 991, "level": 5}, {"ability": 5033, "time": 993, "level": 6}, {"ability": 5032, "time": 1147, "level": 7}, {"ability": 5032, "time": 1221, "level": 8}, {"ability": 5032, "time": 1313, "level": 9}, {"ability": 5940, "time": 1465, "level": 10}, {"ability": 5032, "time": 1507, "level": 11}, {"ability": 5035, "time": 1653, "level": 12}, {"ability": 5033, "time": 1849, "level": 13}, {"ability": 5031, "time": 1975, "level": 14}, {"ability": 5912, "time": 2151, "level": 15}, {"ability": 5031, "time": 2200, "level": 16}], "hero_name": "Kunkka", "item_0_name": "Gauntlets of Strength", "item_1_name": "Crystalys", "item_2_name": "Armlet of Mordiggian", "item_4_name": "Phase Boots", "item_5_name": "Shadow Blade", "leaver_status_name": "NONE", "leaver_status_description": "finished match, no abandon"}, {"account_id": 191823998, "player_slot": 4, "hero_id": 56, "item_0": 98, "item_1": 168, "item_2": 178, "item_3": 24, "item_4": 212, "item_5": 63, "backpack_0": 57, "backpack_1": 46, "backpack_2": 36, "kills": 17, "deaths": 4, "assists": 3, "leaver_status": 0, "last_hits": 147, "denies": 15, "gold_per_min": 631, "xp_per_min": 782, "level": 24, "hero_damage": 30807, "tower_damage": 8708, "hero_healing": 0, "gold": 4590, "gold_spent": 15340, "scaled_hero_damage": 22592, "scaled_tower_damage": 6154, "scaled_hero_healing": 0, "ability_upgrades": [{"ability": 5260, "time": 272, "level": 1}, {"ability": 5261, "time": 424, "level": 2}, {"ability": 5260, "time": 472, "level": 3}, {"ability": 5259, "time": 525, "level": 4}, {"ability": 5260, "time": 614, "level": 5}, {"ability": 5262, "time": 710, "level": 6}, {"ability": 5260, "time": 829, "level": 7}, {"ability": 5261, "time": 888, "level": 8}, {"ability": 5259, "time": 935, "level": 9}, {"ability": 5932, "time": 1025, "level": 10}, {"ability": 5261, "time": 1095, "level": 11}, {"ability": 5262, "time": 1149, "level": 12}, {"ability": 5259, "time": 1245, "level": 13}, {"ability": 5259, "time": 1334, "level": 14}, {"ability": 6104, "time": 1374, "level": 15}, {"ability": 5261, "time": 1498, "level": 16}, {"ability": 5262, "time": 1693, "level": 17}, {"ability": 5943, "time": 1856, "level": 18}], "hero_name": "Clinkz", "item_0_name": "Orchid Malevolence", "item_1_name": "Desolator", "item_2_name": "Soul Ring", "item_3_name": "Ultimate Orb", "item_4_name": "Ring of Aquila", "item_5_name": "Power Treads", "leaver_status_name": "NONE", "leaver_status_description": "finished match, no abandon"}, {"account_id": 342044121, "player_slot": 128, "hero_id": 8, "item_0": 145, "item_1": 36, "item_2": 50, "item_3": 170, "item_4": 46, "item_5": 182, "backpack_0": 0, "backpack_1": 0, "backpack_2": 0, "kills": 4, "deaths": 8, "assists": 4, "leaver_status": 0, "last_hits": 147, "denies": 6, "gold_per_min": 343, "xp_per_min": 365, "level": 16, "hero_damage": 7586, "tower_damage": 114, "hero_healing": 1127, "gold": 945, "gold_spent": 9490, "scaled_hero_damage": 5138, "scaled_tower_damage": 46, "scaled_hero_healing": 731, "ability_upgrades": [{"ability": 5028, "time": 280, "level": 1}, {"ability": 5027, "time": 422, "level": 2}, {"ability": 5028, "time": 493, "level": 3}, {"ability": 5029, "time": 556, "level": 4}, {"ability": 5028, "time": 647, "level": 5}, {"ability": 5030, "time": 711, "level": 6}, {"ability": 5028, "time": 779, "level": 7}, {"ability": 5027, "time": 884, "level": 8}, {"ability": 5027, "time": 932, "level": 9}, {"ability": 5027, "time": 1050, "level": 10}, {"ability": 5921, "time": 1220, "level": 11}, {"ability": 5030, "time": 1284, "level": 12}, {"ability": 5029, "time": 1403, "level": 13}, {"ability": 5029, "time": 1568, "level": 14}, {"ability": 6016, "time": 1745, "level": 15}, {"ability": 5029, "time": 2152, "level": 16}], "hero_name": "Juggernaut", "item_0_name": "Battle Fury", "item_1_name": "Magic Wand", "item_2_name": "Phase Boots", "item_3_name": "Yasha", "item_4_name": "Town Portal Scroll", "item_5_name": "Stout Shield", "leaver_status_name": "NONE", "leaver_status_description": "finished match, no abandon"}, {"account_id": 93463372, "player_slot": 129, "hero_id": 42, "item_0": 182, "item_1": 46, "item_2": 21, "item_3": 1, "item_4": 63, "item_5": 252, "backpack_0": 11, "backpack_1": 20, "backpack_2": 0, "kills": 1, "deaths": 6, "assists": 10, "leaver_status": 0, "last_hits": 135, "denies": 0, "gold_per_min": 291, "xp_per_min": 362, "level": 16, "hero_damage": 8797, "tower_damage": 599, "hero_healing": 437, "gold": 417, "gold_spent": 8575, "scaled_hero_damage": 5923, "scaled_tower_damage": 414, "scaled_hero_healing": 209, "ability_upgrades": [{"ability": 5086, "time": 390, "level": 1}, {"ability": 5088, "time": 451, "level": 2}, {"ability": 5087, "time": 575, "level": 3}, {"ability": 5088, "time": 711, "level": 4}, {"ability": 5088, "time": 829, "level": 5}, {"ability": 5089, "time": 943, "level": 6}, {"ability": 5088, "time": 1060, "level": 7}, {"ability": 5086, "time": 1154, "level": 8}, {"ability": 5086, "time": 1267, "level": 9}, {"ability": 5906, "time": 1346, "level": 10}, {"ability": 5086, "time": 1418, "level": 11}, {"ability": 5089, "time": 1531, "level": 12}, {"ability": 5087, "time": 1769, "level": 13}, {"ability": 5087, "time": 1988, "level": 14}, {"ability": 6145, "time": 2088, "level": 15}, {"ability": 5087, "time": 2166, "level": 16}], "hero_name": "Wraith King", "item_0_name": "Stout Shield", "item_1_name": "Town Portal Scroll", "item_2_name": "Ogre Club", "item_3_name": "Blink Dagger", "item_4_name": "Power Treads", "item_5_name": "Echo Sabre", "leaver_status_name": "NONE", "leaver_status_description": "finished match, no abandon"}, {"account_id": 168508351, "player_slot": 130, "hero_id": 15, "item_0": 50, "item_1": 210, "item_2": 90, "item_3": 0, "item_4": 36, "item_5": 212, "backpack_0": 0, "backpack_1": 0, "backpack_2": 0, "kills": 5, "deaths": 7, "assists": 4, "leaver_status": 0, "last_hits": 144, "denies": 13, "gold_per_min": 374, "xp_per_min": 417, "level": 17, "hero_damage": 15971, "tower_damage": 325, "hero_healing": 0, "gold": 1020, "gold_spent": 10295, "scaled_hero_damage": 10073, "scaled_tower_damage": 205, "scaled_hero_healing": 0, "ability_upgrades": [{"ability": 5083, "time": 366, "level": 1}, {"ability": 5082, "time": 390, "level": 2}, {"ability": 5082, "time": 445, "level": 3}, {"ability": 5084, "time": 501, "level": 4}, {"ability": 5082, "time": 613, "level": 5}, {"ability": 5085, "time": 671, "level": 6}, {"ability": 5082, "time": 789, "level": 7}, {"ability": 5084, "time": 920, "level": 8}, {"ability": 5083, "time": 1045, "level": 9}, {"ability": 5083, "time": 1201, "level": 10}, {"ability": 5084, "time": 1361, "level": 11}, {"ability": 5085, "time": 1420, "level": 12}, {"ability": 5083, "time": 1553, "level": 13}, {"ability": 5084, "time": 1725, "level": 14}, {"ability": 5929, "time": 1741, "level": 15}, {"ability": 6860, "time": 2081, "level": 16}], "hero_name": "Razor", "item_0_name": "Phase Boots", "item_1_name": "Heaven's Halberd", "item_2_name": "Pipe of Insight", "item_4_name": "Magic Wand", "item_5_name": "Ring of Aquila", "leaver_status_name": "NONE", "leaver_status_description": "finished match, no abandon"}, {"account_id": 99515409, "player_slot": 131, "hero_id": 108, "item_0": 178, "item_1": 125, "item_2": 187, "item_3": 180, "item_4": 46, "item_5": 131, "backpack_0": 11, "backpack_1": 0, "backpack_2": 0, "kills": 3, "deaths": 5, "assists": 1, "leaver_status": 0, "last_hits": 106, "denies": 0, "gold_per_min": 303, "xp_per_min": 386, "level": 16, "hero_damage": 16671, "tower_damage": 0, "hero_healing": 0, "gold": 1100, "gold_spent": 8350, "scaled_hero_damage": 9252, "scaled_tower_damage": 0, "scaled_hero_healing": 0, "ability_upgrades": [{"ability": 5613, "time": 276, "level": 1}, {"ability": 5615, "time": 468, "level": 2}, {"ability": 5613, "time": 586, "level": 3}, {"ability": 5614, "time": 710, "level": 4}, {"ability": 5613, "time": 809, "level": 5}, {"ability": 5616, "time": 956, "level": 6}, {"ability": 5613, "time": 1033, "level": 7}, {"ability": 5614, "time": 1102, "level": 8}, {"ability": 5614, "time": 1211, "level": 9}, {"ability": 6967, "time": 1345, "level": 10}, {"ability": 5614, "time": 1413, "level": 11}, {"ability": 5616, "time": 1453, "level": 12}, {"ability": 5615, "time": 1544, "level": 13}, {"ability": 5615, "time": 1786, "level": 14}, {"ability": 6003, "time": 1987, "level": 15}, {"ability": 5615, "time": 2031, "level": 16}], "hero_name": "Underlord", "item_0_name": "Soul Ring", "item_1_name": "Vanguard", "item_2_name": "Medallion of Courage", "item_3_name": "Arcane Boots", "item_4_name": "Town Portal Scroll", "item_5_name": "Hood of Defiance", "leaver_status_name": "NONE", "leaver_status_description": "finished match, no abandon"}, {"account_id": 4294967295, "player_slot": 132, "hero_id": 107, "item_0": 36, "item_1": 40, "item_2": 92, "item_3": 214, "item_4": 46, "item_5": 181, "backpack_0": 0, "backpack_1": 188, "backpack_2": 0, "kills": 4, "deaths": 7, "assists": 7, "leaver_status": 0, "last_hits": 20, "denies": 2, "gold_per_min": 233, "xp_per_min": 358, "level": 15, "hero_damage": 10829, "tower_damage": 0, "hero_healing": 280, "gold": 1523, "gold_spent": 6030, "scaled_hero_damage": 7140, "scaled_tower_damage": 0, "scaled_hero_healing": 200, "ability_upgrades": [{"ability": 5609, "time": 257, "level": 1}, {"ability": 5608, "time": 492, "level": 2}, {"ability": 5608, "time": 654, "level": 3}, {"ability": 5610, "time": 741, "level": 4}, {"ability": 5608, "time": 903, "level": 5}, {"ability": 5612, "time": 1040, "level": 6}, {"ability": 5608, "time": 1077, "level": 7}, {"ability": 5610, "time": 1286, "level": 8}, {"ability": 5610, "time": 1442, "level": 9}, {"ability": 5940, "time": 1727, "level": 10}, {"ability": 5610, "time": 1740, "level": 11}, {"ability": 5612, "time": 1772, "level": 12}, {"ability": 5609, "time": 1852, "level": 13}, {"ability": 5609, "time": 1987, "level": 14}, {"ability": 6203, "time": 2102, "level": 15}], "hero_name": "Earth Spirit", "item_0_name": "Magic Wand", "item_1_name": "Dust of Appearance", "item_2_name": "Urn of Shadows", "item_3_name": "Tranquil Boots", "item_4_name": "Town Portal Scroll", "item_5_name": "Orb of Venom", "leaver_status_name": "NONE", "leaver_status_description": "finished match, no abandon"}], "radiant_win": true, "duration": 1897, "pre_game_duration": 90, "start_time": 1522457120, "match_id": 3808352653, "match_seq_num": 3307532373, "tower_status_radiant": 2038, "tower_status_dire": 0, "barracks_status_radiant": 63, "barracks_status_dire": 0, "cluster": 121, "first_blood_time": 139, "lobby_type": 7, "human_players": 10, "leagueid": 0, "positive_votes": 0, "negative_votes": 0, "game_mode": 22, "flags": 0, "engine": 1, "radiant_score": 33, "dire_score": 17, "picks_bans": [{"is_pick": false, "hero_id": 34, "team": 0, "order": 0}, {"is_pick": false, "hero_id": 59, "team": 0, "order": 1}], "lobby_name": "Ranked", "game_mode_name": "Ranked All Pick", "cluster_name": "US East"}