{"players": [{"account_id": 33907521, "player_slot": 0, "hero_id": 28, "item_0": 65, "item_1": 257, "item_2": 63, "item_3": 249, "item_4": 9, "item_5": 46, "backpack_0": 36, "backpack_1": 0, "backpack_2": 0, "kills": 8, "deaths": 4, "assists": 13, "leaver_status": 0, "last_hits": 60, "denies": 5, "gold_per_min": 429, "xp_per_min": 469, "level": 18, "hero_damage": 11000, "tower_damage": 1897, "hero_healing": 0, "gold": 1696, "gold_spent": 11790, "scaled_hero_damage": 9713, "scaled_tower_damage": 1315, "scaled_hero_healing": 0, "ability_upgrades": [{"ability": 5366, "time": 539, "level": 1}, {"ability": 5526, "time": 598, "level": 2}, {"ability": 5548, "time": 703, "level": 3}, {"ability": 5526, "time": 839, "level": 4}, {"ability": 5366, "time": 964, "level": 5}, {"ability": 5342, "time": 1056, "level": 6}, {"ability": 5366, "time": 1101, "level": 7}, {"ability": 5366, "time": 1255, "level": 8}, {"ability": 5526, "time": 1455, "level": 9}, {"ability": 5910, "time": 1651, "level": 10}, {"ability": 5526, "time": 1688, "level": 11}, {"ability": 5342, "time": 1763, "level": 12}, {"ability": 5548, "time": 1866, "level": 13}, {"ability": 5548, "time": 1894, "level": 14}, {"ability": 5993, "time": 1954, "level": 15}, {"ability": 5548, "time": 2126, "level": 16}, {"ability": 5342, "time": 2380, "level": 17}], "hero_name": "Slardar", "item_0_name": "Hand of Midas", "item_1_name": "Tome of Knowledge", "item_2_name": "Power Treads", "item_3_name": "Silver Edge", "item_4_name": "Platemail", "item_5_name": "Town Portal Scroll", "leaver_status_name": "NONE", "leaver_status_description": "finished match, no abandon"}, {"account_id": 4294967295, "player_slot": 1, "hero_id": 6, "item_0": 263, "item_1": 147, "item_2": 46, "item_3": 63, "item_4": 212, "item_5": 60, "backpack_0": 0, "backpack_1": 0, "backpack_2": 0, "kills": 8, "deaths": 3, "assists": 17, "leaver_status": 0, "last_hits": 101, "denies": 12, "gold_per_min": 480, "xp_per_min": 591, "level": 21, "hero_damage": 19270, "tower_damage": 11300, "hero_healing": 0, "gold": 1675, "gold_spent": 13470, "scaled_hero_damage": 13331, "scaled_tower_damage": 8119, "scaled_hero_healing": 0, "ability_upgrades": [{"ability": 5021, "time": 516, "level": 1}, {"ability": 5066, "time": 559, "level": 2}, {"ability": 5021, "time": 636, "level": 3}, {"ability": 5130, "time": 710, "level": 4}, {"ability": 5021, "time": 813, "level": 5}, {"ability": 5022, "time": 881, "level": 6}, {"ability": 5021, "time": 962, "level": 7}, {"ability": 5066, "time": 1070, "level": 8}, {"ability": 5066, "time": 1141, "level": 9}, {"ability": 5921, "time": 1216, "level": 10}, {"ability": 5066, "time": 1343, "level": 11}, {"ability": 5022, "time": 1453, "level": 12}, {"ability": 5130, "time": 1567, "level": 13}, {"ability": 5130, "time": 1689, "level": 14}, {"ability": 6016, "time": 1856, "level": 15}, {"ability": 5130, "time": 2022, "level": 16}, {"ability": 5022, "time": 2129, "level": 17}, {"ability": 6280, "time": 2363, "level": 18}], "hero_name": "Drow Ranger", "item_0_name": "Hurricane Pike", "item_1_name": "Manta Style", "item_2_name": "Town Portal Scroll", "item_3_name": "Power Treads", "item_4_name": "Ring of Aquila", "item_5_name": "Point Booster", "leaver_status_name": "NONE", "leaver_status_description": "finished match, no abandon"}, {"account_id": 4294967295, "player_slot": 2, "hero_id": 102, "item_0": 50, "item_1": 267, "item_2": 40, "item_3": 53, "item_4": 81, "item_5": 61, "backpack_0": 0, "backpack_1": 0, "backpack_2": 46, "kills": 3, "deaths": 3, "assists": 29, "leaver_status": 0, "last_hits": 62, "denies": 9, "gold_per_min": 436, "xp_per_min": 670, "level": 22, "hero_damage": 19677, "tower_damage": 1408, "hero_healing": 4007, "gold": 1638, "gold_spent": 12355, "scaled_hero_damage": 12916, "scaled_tower_damage": 911, "scaled_hero_healing": 1808, "ability_upgrades": [{"ability": 5586, "time": 530, "level": 1}, {"ability": 5190, "time": 583, "level": 2}, {"ability": 5586, "time": 706, "level": 3}, {"ability": 5190, "time": 829, "level": 4}, {"ability": 5586, "time": 929, "level": 5}, {"ability": 5588, "time": 1040, "level": 6}, {"ability": 5586, "time": 1118, "level": 7}, {"ability": 5550, "time": 1223, "level": 8}, {"ability": 5550, "time": 1345, "level": 9}, {"ability": 6017, "time": 1439, "level": 10}, {"ability": 5550, "time": 1495, "level": 11}, {"ability": 5588, "time": 1615, "level": 12}, {"ability": 5550, "time": 1638, "level": 13}, {"ability": 5190, "time": 1701, "level": 14}, {"ability": 5190, "time": 1797, "level": 15}, {"ability": 5933, "time": 1828, "level": 16}, {"ability": 5588, "time": 1924, "level": 17}, {"ability": 5952, "time": 2131, "level": 18}], "hero_name": "Abaddon", "item_0_name": "Phase Boots", "item_2_name": "Dust of Appearance", "item_3_name": "Reaver", "item_4_name": "Vladmir's Offering", "item_5_name": "Vitality Booster", "leaver_status_name": "NONE", "leaver_status_description": "finished match, no abandon"}, {"account_id": 4294967295, "player_slot": 3, "hero_id": 98, "item_0": 1, "item_1": 180, "item_2": 100, "item_3": 259, "item_4": 232, "item_5": 34, "backpack_0": 0, "backpack_1": 0, "backpack_2": 0, "kills": 8, "deaths": 10, "assists": 19, "leaver_status": 0, "last_hits": 82, "denies": 1, "gold_per_min": 424, "xp_per_min": 413, "level": 17, "hero_damage": 19474, "tower_damage": 618, "hero_healing": 0, "gold": 662, "gold_spent": 11700, "scaled_hero_damage": 13943, "scaled_tower_damage": 465, "scaled_hero_healing": 0, "ability_upgrades": [{"ability": 5549, "time": 531, "level": 1}, {"ability": 5115, "time": 586, "level": 2}, {"ability": 5115, "time": 694, "level": 3}, {"ability": 5549, "time": 826, "level": 4}, {"ability": 5549, "time": 983, "level": 5}, {"ability": 5121, "time": 1046, "level": 6}, {"ability": 5632, "time": 1288, "level": 7}, {"ability": 5549, "time": 1377, "level": 8}, {"ability": 5115, "time": 1461, "level": 9}, {"ability": 5996, "time": 1496, "level": 10}, {"ability": 5115, "time": 1639, "level": 11}, {"ability": 5121, "time": 1673, "level": 12}, {"ability": 5632, "time": 1795, "level": 13}, {"ability": 5632, "time": 1898, "level": 14}, {"ability": 5979, "time": 1920, "level": 15}, {"ability": 5632, "time": 2192, "level": 16}], "hero_name": "Timbersaw", "item_0_name": "Blink Dagger", "item_1_name": "Arcane Boots", "item_2_name": "Eul's Scepter of Divinity", "item_4_name": "Aether Lens", "item_5_name": "Magic Stick", "leaver_status_name": "NONE", "leaver_status_description": "finished match, no abandon"}, {"account_id": 108994455, "player_slot": 4, "hero_id": 73, "item_0": 0, "item_1": 127, "item_2": 48, "item_3": 112, "item_4": 229, "item_5": 137, "backpack_0": 36, "backpack_1": 0, "backpack_2": 0, "kills": 9, "deaths": 3, "assists": 16, "leaver_status": 0, "last_hits": 212, "denies": 13, "gold_per_min": 622, "xp_per_min": 656, "level": 22, "hero_damage": 26146, "tower_damage": 621, "hero_healing": 0, "gold": 824, "gold_spent": 20955, "scaled_hero_damage": 17515, "scaled_tower_damage": 266, "scaled_hero_healing": 0, "ability_upgrades": [{"ability": 5119, "time": 534, "level": 1}, {"ability": 5322, "time": 598, "level": 2}, {"ability": 5119, "time": 639, "level": 3}, {"ability": 5322, "time": 759, "level": 4}, {"ability": 5322, "time": 894, "level": 5}, {"ability": 5067, "time": 1033, "level": 6}, {"ability": 5322, "time": 1142, "level": 7}, {"ability": 5119, "time": 1266, "level": 8}, {"ability": 5119, "time": 1345, "level": 9}, {"ability": 6016, "time": 1467, "level": 10}, {"ability": 5114, "time": 1550, "level": 11}, {"ability": 5114, "time": 1610, "level": 12}, {"ability": 5114, "time": 1632, "level": 13}, {"ability": 5114, "time": 1751, "level": 14}, {"ability": 5976, "time": 1830, "level": 15}, {"ability": 5067, "time": 1888, "level": 16}, {"ability": 5067, "time": 2097, "level": 17}, {"ability": 7122, "time": 2292, "level": 18}], "hero_name": "Alchemist", "item_1_name": "Blade Mail", "item_2_name": "Boots of Travel", "item_3_name": "Assault Cuirass", "item_4_name": "Solar Crest", "item_5_name": "Radiance", "leaver_status_name": "NONE", "leaver_status_description": "finished match, no abandon"}, {"account_id": 103233418, "player_slot": 128, "hero_id": 69, "item_0": 11, "item_1": 50, "item_2": 178, "item_3": 137, "item_4": 252, "item_5": 0, "backpack_0": 0, "backpack_1": 0, "backpack_2": 0, "kills": 6, "deaths": 5, "assists": 10, "leaver_status": 0, "last_hits": 84, "denies": 3, "gold_per_min": 364, "xp_per_min": 461, "level": 18, "hero_damage": 19404, "tower_damage": 25, "hero_healing": 0, "gold": 616, "gold_spent": 10650, "scaled_hero_damage": 11449, "scaled_tower_damage": 23, "scaled_hero_healing": 0, "ability_upgrades": [{"ability": 5524, "time": 478, "level": 1}, {"ability": 5192, "time": 653, "level": 2}, {"ability": 5192, "time": 746, "level": 3}, {"ability": 5065, "time": 922, "level": 4}, {"ability": 5065, "time": 1054, "level": 5}, {"ability": 5369, "time": 1183, "level": 6}, {"ability": 5065, "time": 1192, "level": 7}, {"ability": 5065, "time": 1326, "level": 8}, {"ability": 5192, "time": 1520, "level": 9}, {"ability": 5192, "time": 1557, "level": 10}, {"ability": 5524, "time": 1720, "level": 11}, {"ability": 5369, "time": 1771, "level": 12}, {"ability": 5524, "time": 1887, "level": 13}, {"ability": 6370, "time": 1905, "level": 14}, {"ability": 5973, "time": 1924, "level": 15}, {"ability": 5524, "time": 2127, "level": 16}, {"ability": 5369, "time": 2229, "level": 17}], "hero_name": "Doom", "item_0_name": "Quelling Blade", "item_1_name": "Phase Boots", "item_2_name": "Soul Ring", "item_3_name": "Radiance", "item_4_name": "Echo Sabre", "leaver_status_name": "NONE", "leaver_status_description": "finished match, no abandon"}, {"account_id": 282099084, "player_slot": 129, "hero_id": 29, "item_0": 145, "item_1": 36, "item_2": 63, "item_3": 168, "item_4": 0, "item_5": 182, "backpack_0": 0, "backpack_1": 0, "backpack_2": 0, "kills": 7, "deaths": 11, "assists": 4, "leaver_status": 0, "last_hits": 144, "denies": 10, "gold_per_min": 400, "xp_per_min": 505, "level": 19, "hero_damage": 12565, "tower_damage": 0, "hero_healing": 0, "gold": 760, "gold_spent": 10140, "scaled_hero_damage": 8608, "scaled_tower_damage": 0, "scaled_hero_healing": 0, "ability_upgrades": [{"ability": 5118, "time": 434, "level": 1}, {"ability": 5191, "time": 591, "level": 2}, {"ability": 5118, "time": 676, "level": 3}, {"ability": 5191, "time": 780, "level": 4}, {"ability": 5118, "time": 839, "level": 5}, {"ability": 5193, "time": 917, "level": 6}, {"ability": 5118, "time": 1116, "level": 7}, {"ability": 5191, "time": 1197, "level": 8}, {"ability": 5191, "time": 1306, "level": 9}, {"ability": 6945, "time": 1377, "level": 10}, {"ability": 5234, "time": 1517, "level": 11}, {"ability": 5193, "time": 1607, "level": 12}, {"ability": 5234, "time": 1690, "level": 13}, {"ability": 5234, "time": 1846, "level": 14}, {"ability": 5234, "time": 1886, "level": 15}, {"ability": 6447, "time": 1906, "level": 16}, {"ability": 5193, "time": 2209, "level": 17}], "hero_name": "Tidehunter", "item_0_name": "Battle Fury", "item_1_name": "Magic Wand", "item_2_name": "Power Treads", "item_3_name": "Desolator", "item_5_name": "Stout Shield", "leaver_status_name": "NONE", "leaver_status_description": "finished match, no abandon"}, {"account_id": 113484438, "player_slot": 130, "hero_id": 12, "item_0": 206, "item_1": 180, "item_2": 244, "item_3": 31, "item_4": 27, "item_5": 212, "backpack_0": 0, "backpack_1": 16, "backpack_2": 0, "kills": 3, "deaths": 8, "assists": 14, "leaver_status": 0, "last_hits": 59, "denies": 4, "gold_per_min": 253, "xp_per_min": 347, "level": 15, "hero_damage": 14189, "tower_damage": 0, "hero_healing": 0, "gold": 542, "gold_spent": 7145, "scaled_hero_damage": 10989, "scaled_tower_damage": 0, "scaled_hero_healing": 0, "ability_upgrades": [{"ability": 5320, "time": 411, "level": 1}, {"ability": 5340, "time": 576, "level": 2}, {"ability": 5320, "time": 673, "level": 3}, {"ability": 5233, "time": 804, "level": 4}, {"ability": 5320, "time": 1014, "level": 5}, {"ability": 5527, "time": 1140, "level": 6}, {"ability": 5320, "time": 1233, "level": 7}, {"ability": 5340, "time": 1429, "level": 8}, {"ability": 5340, "time": 1495, "level": 9}, {"ability": 5233, "time": 1557, "level": 10}, {"ability": 5233, "time": 1661, "level": 11}, {"ability": 5233, "time": 1773, "level": 12}, {"ability": 5527, "time": 1958, "level": 13}, {"ability": 5340, "time": 2111, "level": 14}, {"ability": 5906, "time": 2234, "level": 15}], "hero_name": "Phantom Lancer", "item_0_name": "Rod of Atos", "item_1_name": "Arcane Boots", "item_2_name": "Wind Lace", "item_3_name": "Cloak", "item_4_name": "Ring of Regen", "item_5_name": "Ring of Aquila", "leaver_status_name": "NONE", "leaver_status_description": "finished match, no abandon"}, {"account_id": 4294967295, "player_slot": 131, "hero_id": 50, "item_0": 77, "item_1": 50, "item_2": 152, "item_3": 24, "item_4": 240, "item_5": 65, "backpack_0": 0, "backpack_1": 0, "backpack_2": 0, "kills": 4, "deaths": 8, "assists": 4, "leaver_status": 0, "last_hits": 112, "denies": 28, "gold_per_min": 344, "xp_per_min": 473, "level": 18, "hero_damage": 13168, "tower_damage": 0, "hero_healing": 0, "gold": 59, "gold_spent": 9345, "scaled_hero_damage": 8318, "scaled_tower_damage": 0, "scaled_hero_healing": 0, "ability_upgrades": [{"ability": 5341, "time": 422, "level": 1}, {"ability": 5587, "time": 550, "level": 2}, {"ability": 5341, "time": 618, "level": 3}, {"ability": 5587, "time": 663, "level": 4}, {"ability": 5341, "time": 743, "level": 5}, {"ability": 5117, "time": 848, "level": 6}, {"ability": 5341, "time": 908, "level": 7}, {"ability": 5587, "time": 983, "level": 8}, {"ability": 5525, "time": 1066, "level": 9}, {"ability": 5942, "time": 1189, "level": 10}, {"ability": 5587, "time": 1281, "level": 11}, {"ability": 5117, "time": 1432, "level": 12}, {"ability": 5525, "time": 1536, "level": 13}, {"ability": 5525, "time": 1727, "level": 14}, {"ability": 6232, "time": 1927, "level": 15}, {"ability": 5525, "time": 1972, "level": 16}, {"ability": 5117, "time": 2224, "level": 17}], "hero_name": "Dazzle", "item_0_name": "Null Talisman", "item_1_name": "Phase Boots", "item_2_name": "Shadow Blade", "item_3_name": "Ultimate Orb", "item_4_name": "Blight Stone", "item_5_name": "Hand of Midas", "leaver_status_name": "NONE", "leaver_status_description": "finished match, no abandon"}, {"account_id": 4294967295, "player_slot": 132, "hero_id": 44, "item_0": 182, "item_1": 170, "item_2": 81, "item_3": 56, "item_4": 63, "item_5": 36, "backpack_0": 40, "backpack_1": 11, "backpack_2": 0, "kills": 2, "deaths": 8, "assists": 14, "leaver_status": 0, "last_hits": 57, "denies": 8, "gold_per_min": 305, "xp_per_min": 361, "level": 15, "hero_damage": 9452, "tower_damage": 0, "hero_healing": 867, "gold": 827, "gold_spent": 7870, "scaled_hero_damage": 6901, "scaled_tower_damage": 0, "scaled_hero_healing": 238, "ability_upgrades": [{"ability": 5368, "time": 438, "level": 1}, {"ability": 5116, "time": 683, "level": 2}, {"ability": 5116, "time": 750, "level": 3}, {"ability": 5068, "time": 863, "level": 4}, {"ability": 5068, "time": 1006, "level": 5}, {"ability": 5236, "time": 1083, "level": 6}, {"ability": 5116, "time": 1239, "level": 7}, {"ability": 5116, "time": 1354, "level": 8}, {"ability": 5068, "time": 1438, "level": 9}, {"ability": 5068, "time": 1566, "level": 10}, {"ability": 5902, "time": 1690, "level": 11}, {"ability": 5236, "time": 1785, "level": 12}, {"ability": 5368, "time": 1979, "level": 13}, {"ability": 5368, "time": 2108, "level": 14}, {"ability": 6603, "time": 2243, "level": 15}], "hero_name": "Phantom Assassin", "item_0_name": "Stout Shield", "item_1_name": "Yasha", "item_2_name": "Vladmir's Offering", "item_3_name": "Ring of Health", "item_4_name": "Power Treads", "item_5_name": "Magic Wand", "leaver_status_name": "NONE", "leaver_status_description": "finished match, no abandon"}], "radiant_win": true, "duration": 1884, "pre_game_duration": 90, "start_time": 1521172599, "match_id": 3783125102, "match_seq_num": 3286078832, "tower_status_radiant": 2047, "tower_status_dire": 0, "barracks_status_radiant": 63, "barracks_status_dire": 0, "cluster": 121, "first_blood_time": 83, "lobby_type": 0, "human_players": 10, "leagueid": 0, "positive_votes": 0, "negative_votes": 0, "game_mode": 18, "flags": 0, "engine": 1, "radiant_score": 40, "dire_score": 23, "lobby_name": "Public matchmaking", "game_mode_name": "Ability Draft", "cluster_name": "US East"}